ns/__init__.py
ns/api.py
ns/models.py
ns_api-0.0.1.dist-info/LICENSE
ns_api-0.0.1.dist-info/METADATA
ns_api-0.0.1.dist-info/WHEEL
ns_api-0.0.1.dist-info/top_level.txt
ns_api-0.0.1.dist-info/RECORD
