Metadata-Version: 2.1
Name: ns-api
Version: 0.0.1
Summary: Wrapper for the NS api
Home-page: http://github.com/Shiqan/ns-api
Author: Shiqan
License: MIT
Keywords: api ns nederlandse spoorwegen dutch railway
Platform: UNKNOWN
Classifier: Development Status :: 3 - Alpha
Classifier: Intended Audience :: Developers
Classifier: License :: OSI Approved :: MIT License
Classifier: Programming Language :: Python :: 3.7
Requires-Dist: aiohttp
Requires-Dist: dataclasses-json
Requires-Dist: requests
